vending_machine/vending_machine_18105070.v
module vending_machine_18105070(
    input clk,
    input rst,
    input [1:0] in, // 01 = 5 rs, 10 = 10 rs
    output reg out,
    output reg [1:0] change
);

    // Parameters for states
    parameter s0 = 2'b00; // $0
    parameter s1 = 2'b01; // $5
    parameter s2 = 2'b10; // $10

    reg [1:0] c_state, n_state;

    // State transition logic
    always @ (posedge clk or posedge rst) begin
        if (rst) begin
            c_state <= s0;
            out <= 0;
            change <= 2'b00;
        end else begin
            c_state <= n_state;
        end
    end

    // Next state and output logic
    always @ (*) begin
        // Default values
        n_state = c_state;
        out = 0;
        change = 2'b00;

        case (c_state)
            s0: begin // State $0
                if (in == 2'b01) begin
                    n_state = s1;
                end else if (in == 2'b10) begin
                    n_state = s2;
                end
            end

            s1: begin // State $5
                if (in == 2'b01) begin
                    n_state = s2;
                end else if (in == 2'b10) begin
                    n_state = s0;
                    out = 1; // Transaction complete
                end else if (in == 2'b00) begin
                    n_state = s0;
                    change = 2'b01; // Return $5
                end
            end

            s2: begin // State $10
                if (in == 2'b01) begin
                    n_state = s0;
                    out = 1; // Transaction complete
                end else if (in == 2'b10) begin
                    n_state = s0;
                    out = 1; // Transaction complete
                    change = 2'b01; // Return $5
                end else if (in == 2'b00) begin
                    n_state = s0;
                    change = 2'b10; // Return $10
                end
            end

            default: begin
                n_state = s0; // Default to initial state
            end
        endcase
    end
endmodule

vending_machine/vending_machine_tb.v
module vending_machine_tb;

    // Inputs
    reg clk;
    reg [1:0] in;
    reg rst;

    // Outputs
    wire out;
    wire [1:0] change;

    // Instantiate the Unit Under Test (UUT)
    vending_machine_18105070 uut (
        .clk(clk),
        .rst(rst),
        .in(in),
        .out(out),
        .change(change)
    );

    // Clock generation
    always #5 clk = ~clk;

    initial begin
        // Initialize Inputs
        $dumpfile("vending_machine_18105070.vcd");
        $dumpvars(0, vending_machine_tb);
        
        clk = 0;
        rst = 1;
        in = 0;

        // Apply Reset
        #10 rst = 0;

        // Test Input Scenarios
        #10 in = 2'b01; // Add $5
        #10 in = 2'b10; // Add $10
        #10 in = 2'b00; // No input, check outputs

        // Reset and Test Overpayment
        #20 rst = 1;    // Reset
        #10 rst = 0;
        #10 in = 2'b10; // Add $10
        #10 in = 2'b10; // Add $10 (overpayment)
        #10 in = 2'b00; // No input, check outputs

        // End Simulation
        #50 $finish;
    end

endmodule

vending_machine/vending_machine_18105070.vcd
$date
	Wed Jan 15 19:40:24 2025
$end
$version
	Icarus Verilog
$end
$timescale
	1s
$end
$scope module vending_machine_tb $end
$var wire 1 ! out $end
$var wire 2 " change [1:0] $end
$var reg 1 # clk $end
$var reg 2 $ in [1:0] $end
$var reg 1 % rst $end
$scope module uut $end
$var wire 1 # clk $end
$var wire 2 & in [1:0] $end
$var wire 1 % rst $end
$var parameter 2 ' s0 $end
$var parameter 2 ( s1 $end
$var parameter 2 ) s2 $end
$var reg 2 * c_state [1:0] $end
$var reg 2 + change [1:0] $end
$var reg 2 , n_state [1:0] $end
$var reg 1 ! out $end
$upscope $end
$upscope $end
$enddefinitions $end
$comment Show the parameter values. $end
$dumpall
b10 )
b1 (
b0 '
$end
#0
$dumpvars
b0 ,
b0 +
b0 *
b0 &
1%
b0 $
0#
b0 "
0!
$end
#5
1#
#10
0#
0%
#15
1#
#20
b1 ,
0#
b1 $
b1 &
#25
b10 ,
b1 *
1#
#30
1!
b0 ,
0#
b10 $
b10 &
#35
b10 ,
0!
b0 *
1#
#40
b0 ,
0#
b0 $
b0 &
#45
1#
#50
0#
#55
1#
#60
0#
1%
#65
1#
#70
0#
0%
#75
1#
#80
b10 ,
0#
b10 $
b10 &
#85
b1 "
b1 +
1!
b0 ,
b10 *
1#
#90
0#
#95
b10 ,
b0 "
b0 +
0!
b0 *
1#
#100
b0 ,
0#
b0 $
b0 &
